reg2info/__init__.py
reg2info/get_equation.py
reg2info/get_plot.py
reg2info-1.0.0.dist-info/LICENSE
reg2info-1.0.0.dist-info/METADATA
reg2info-1.0.0.dist-info/WHEEL
reg2info-1.0.0.dist-info/top_level.txt
reg2info-1.0.0.dist-info/RECORD
