Metadata-Version: 2.1
Name: reg2info
Version: 1.0.0
Summary: An awesome package that allows getting meaningful information from a Linear regression model
Home-page: https://github.com/mohamedabidi97/reg2info.git
Author: Mohamed Abidi
Author-email: abidi.contact@gmail.com
License: UNKNOWN
Platform: UNKNOWN
Classifier: Programming Language :: Python :: 3
Classifier: License :: OSI Approved :: MIT License
Classifier: Operating System :: OS Independent
License-File: LICENSE
